py_cmd_tool/__init__.py
py_cmd_tool/version.py
py_cmd_tool-1.0.1.dist-info/LICENSE
py_cmd_tool-1.0.1.dist-info/METADATA
py_cmd_tool-1.0.1.dist-info/WHEEL
py_cmd_tool-1.0.1.dist-info/top_level.txt
py_cmd_tool-1.0.1.dist-info/RECORD
