Metadata-Version: 2.1
Name: py-cmd-tool
Version: 1.0.1
Summary: Python command-line tool helper library
Home-page: https://gitlab.com/bredbeddle-open/cmd-tool
Author: Curtis Forrester
License: MIT
Keywords: argparse tools
Platform: UNKNOWN
Classifier: Development Status :: 3 - Alpha
Classifier: Environment :: Console
Classifier: Intended Audience :: Developers
Classifier: License :: OSI Approved :: MIT License
Classifier: Programming Language :: Python
Classifier: Programming Language :: Python :: 3
Classifier: Programming Language :: Python :: 3.7
Classifier: Programming Language :: Python :: 3.9
Classifier: Topic :: Software Development :: Libraries
Requires-Python: >=3.7
Requires-Dist: pkg-version-mgr
